{
  "projects": [
    {
      "url": "https://github.com/ThiaudioTT/random-quote-machine",
      "title": "Random Quote Machine",
      "description": "It generates a random quote from an API and allows the user to tweet the quote.",
      "isClosedSource": false,
      "image": "/assets/uploads/demo.png",
      "technologies": [
        "react",
        "next.js",
        "typescript",
        "tailwindcss"
      ],
      "image_src": "/assets/uploads/demo.png"
    },
    {
      "url": "https://github.com/ThiaudioTT/VollMedApi",
      "title": "Vollmed API",
      "description": "A REST API for a medical clinic\n\n",
      "technologies": [
        "springBoot",
        "flyway",
        "mySql",
        "beanValidator",
        "lombok"
      ],
      "image_src": "/assets/uploads/code.png",
      "isClosedSource": false
    },
    {
      "url": "https://github.com/ThiaudioTT/tower-of-hanoi",
      "title": "Tower of Hanoi",
      "description": "Tower of Hanoi game written in Clojure",
      "technologies": [
        "ClojureScript",
        "Clojure",
        "Reagent",
        "Shadow-cljs"
      ],
      "image_src": "/assets/uploads/hanoi-demo.png",
      "isClosedSource": false
    },
    {
      "url": "https://github.com/ThiaudioTT/hoi4-presence",
      "title": "Hoi4 mod",
      "description": "A mod for Hearts of Iron 4 who communicates with discord API",
      "technologies": [
        "python",
        "pypresence",
        "pyinstaller"
      ],
      "image_src": "/assets/uploads/demohoi4.png",
      "isClosedSource": false
    },
    {
      "url": "https://github.com/ThiaudioTT/UberEmailService",
      "image_src": "/assets/uploads/uber-email-service.png",
      "description": " Uber Backend Challenge about email services",
      "technologies": [
        "java21",
        "lombok",
        "aws-ses",
        "sendgrid",
        "spring-boot"
      ],
      "title": "Uber Email Service",
      "isClosedSource": false
    },
    {
      "url": "https://github.com/ThiaudioTT/personalities-api",
      "isClosedSource": false,
      "title": "Personalities API",
      "description": "A CRUD api to manage personalities",
      "technologies": [
        "Go",
        "docker",
        "GorillaMux",
        "PostgreSQL",
        "Migrate",
        "Validate"
      ],
      "image_src": "/assets/uploads/personalities-api.png"
    }
  ]
}
